piepline/__init__.py
piepline/predict.py
piepline/train.py
piepline/builtin/__init__.py
piepline/builtin/monitors/__init__.py
piepline/builtin/monitors/mpl.py
piepline/builtin/monitors/tensorboard.py
piepline/data_processor/__init__.py
piepline/data_processor/data_processor.py
piepline/data_producer/__init__.py
piepline/data_producer/data_producer.py
piepline/data_producer/datasets.py
piepline/monitoring/__init__.py
piepline/monitoring/hub.py
piepline/monitoring/monitors.py
piepline/train_config/__init__.py
piepline/train_config/metrics.py
piepline/train_config/metrics_processor.py
piepline/train_config/stages.py
piepline/train_config/train_config.py
piepline/utils/__init__.py
piepline/utils/checkpoints_manager.py
piepline/utils/events_system.py
piepline/utils/fsm.py
piepline/utils/messages_system.py
piepline/utils/utils.py
piepline-0.3.2.dist-info/LICENSE
piepline-0.3.2.dist-info/METADATA
piepline-0.3.2.dist-info/WHEEL
piepline-0.3.2.dist-info/top_level.txt
piepline-0.3.2.dist-info/RECORD
